codingpoe/__init__.py
codingpoe/api.py
codingpoe/proxies.py
codingpoe/queries.py
codingpoe-1.1.0.dist-info/LICENSE
codingpoe-1.1.0.dist-info/METADATA
codingpoe-1.1.0.dist-info/WHEEL
codingpoe-1.1.0.dist-info/top_level.txt
codingpoe-1.1.0.dist-info/RECORD
