Metadata-Version: 2.1
Name: codingpoe
Version: 1.1.0
Summary: A simple package that use Poe AI models
Home-page: https://github.com/codingtuto/codingpoe
Author: Coding Team
Keywords: python,poe,quora,chatgpt,claude,poe-api,api,codingteam
Classifier: Programming Language :: Python :: 3
Classifier: License :: OSI Approved :: GNU General Public License (GPL)
Classifier: Operating System :: OS Independent
Requires-Python: >=3.7
License-File: LICENSE
Requires-Dist: httpx (==0.24.1)
Requires-Dist: ballyregan (==1.0.6)
Requires-Dist: websocket-client
